FastDevCommon/__init__.py
FastDevCommon/_client/__init__.py
FastDevCommon/_client/http_client.py
FastDevCommon/_client/redis_client.py
FastDevCommon/_client/nacos/__init__.py
FastDevCommon/_client/nacos/async_client.py
FastDevCommon/_client/nacos/client_config.py
FastDevCommon/_client/nacos/factory.py
FastDevCommon/_client/nacos/interfaces.py
FastDevCommon/_client/nacos/nacos_client.py
FastDevCommon/_client/nacos/sync_client.py
FastDevCommon/_decorators/__init__.py
FastDevCommon/_decorators/retry.py
FastDevCommon/_logger/__init__.py
FastDevCommon/_logger/logger.py
FastDevCommon/_result/__init__.py
FastDevCommon/_result/case_utils.py
FastDevCommon/_result/operate_enum.py
FastDevCommon/_result/operate_result.py
FastDevCommon/_schedulers/__init__.py
FastDevCommon/_schedulers/generate_scheduler.py
FastDevCommon/_schema/__init__.py
FastDevCommon/_schema/base_schema.py
FastDevCommon/_server/__init__.py
FastDevCommon/_server/base_app.py
FastDevCommon/_server/exceptions/__init__.py
FastDevCommon/_server/exceptions/exception.py
FastDevCommon/_task/__init__.py
FastDevCommon/_task/async_task_pool.py
FastDevCommon/_task/base_task.py
FastDevCommon/base/__init__.py
FastDevCommon/base/base_dao.py
FastDevCommon/base/base_do.py
FastDevCommon/base/base_dto.py
FastDevCommon/utils/__init__.py
FastDevCommon/utils/sha1.py
FastDevCommon/utils/snowflake_id_generator.py
FastDevCommon/utils/utils.py
fastdevcommon-0.2.1.dist-info/licenses/LICENSE
fastdevcommon-0.2.1.dist-info/METADATA
fastdevcommon-0.2.1.dist-info/WHEEL
fastdevcommon-0.2.1.dist-info/top_level.txt
fastdevcommon-0.2.1.dist-info/RECORD
