Metadata-Version: 2.4
Name: fastdevcommon
Version: 0.2.1
Summary: A common development component
Home-page: https://github.com/hwzlikewyh/FastDevCommon.git
Author: hwzlikewyh
Author-email: hwzlikewyh@163.com
License: MIT
License-File: LICENSE
Requires-Dist: aiohappyeyeballs
Requires-Dist: aiohttp
Requires-Dist: aioredis
Requires-Dist: aiosignal
Requires-Dist: annotated-types
Requires-Dist: async-timeout
Requires-Dist: attrs
Requires-Dist: backports.tarfile
Requires-Dist: certifi
Requires-Dist: charset-normalizer
Requires-Dist: colorama
Requires-Dist: docutils
Requires-Dist: frozenlist
Requires-Dist: id
Requires-Dist: idna
Requires-Dist: importlib_metadata
Requires-Dist: jaraco.classes
Requires-Dist: jaraco.context
Requires-Dist: jaraco.functools
Requires-Dist: keyring
Requires-Dist: loguru
Requires-Dist: markdown-it-py
Requires-Dist: mdurl
Requires-Dist: more-itertools
Requires-Dist: multidict
Requires-Dist: nh3
Requires-Dist: packaging
Requires-Dist: propcache
Requires-Dist: pydantic
Requires-Dist: pydantic_core
Requires-Dist: Pygments
Requires-Dist: pywin32-ctypes
Requires-Dist: readme_renderer
Requires-Dist: redis
Requires-Dist: requests
Requires-Dist: requests-toolbelt
Requires-Dist: rfc3986
Requires-Dist: rich
Requires-Dist: typing-inspection
Requires-Dist: typing_extensions
Requires-Dist: urllib3
Requires-Dist: win32_setctime
Requires-Dist: yarl
Requires-Dist: zipp
Requires-Dist: nacos-sdk-python
Requires-Dist: uvicorn
Requires-Dist: fastapi
Requires-Dist: sqlalchemy
Dynamic: author
Dynamic: author-email
Dynamic: description-content-type
Dynamic: home-page
Dynamic: license
Dynamic: license-file
Dynamic: requires-dist
Dynamic: summary
